blastai/__init__.py
blastai/cache.py
blastai/cli.py
blastai/config.py
blastai/default_config.yaml
blastai/engine.py
blastai/executor.py
blastai/logging_setup.py
blastai/models.py
blastai/planner.py
blastai/resource_manager.py
blastai/response.py
blastai/scheduler.py
blastai/secrets.py
blastai/server.py
blastai/tools.py
blastai/utils.py
blastai/frontend/next.config.js
blastai/frontend/package.json
blastai/frontend/postcss.config.js
blastai/frontend/tailwind.config.js
blastai/frontend/tsconfig.json
blastai/frontend/components/ChatInput.tsx
blastai/frontend/components/Header.tsx
blastai/frontend/components/LoadingLogo.tsx
blastai/frontend/components/TaskBox.tsx
blastai/frontend/pages/_app.tsx
blastai/frontend/pages/index.tsx
blastai/frontend/public/assets/blast_icon_only.ico
blastai/frontend/public/assets/blast_icon_only.png
blastai/frontend/public/assets/blast_icon_only.sketchpad
blastai/frontend/public/assets/blast_icon_only.svg
blastai/frontend/styles/globals.css
blastai-0.1.6.dist-info/licenses/LICENSE
blastai-0.1.6.dist-info/METADATA
blastai-0.1.6.dist-info/WHEEL
blastai-0.1.6.dist-info/entry_points.txt
blastai-0.1.6.dist-info/top_level.txt
blastai-0.1.6.dist-info/RECORD
