Metadata-Version: 2.4
Name: blastai
Version: 0.1.6
Summary: Browser-LLM Auto-Scaling Technology
Author: Caleb Winston
License-Expression: MIT
Project-URL: Homepage, https://github.com/stanford-mast/blast
Project-URL: Documentation, https://github.com/stanford-mast/blast#readme
Project-URL: Issues, https://github.com/stanford-mast/blast/issues
Classifier: Development Status :: 3 - Alpha
Classifier: Intended Audience :: Developers
Classifier: Programming Language :: Python :: 3
Classifier: Programming Language :: Python :: 3.11
Classifier: Topic :: Software Development :: Libraries :: Python Modules
Classifier: Topic :: Internet :: WWW/HTTP :: Browsers
Requires-Python: >=3.11
License-File: LICENSE
Requires-Dist: pydantic>=2.0
Requires-Dist: browser-use>=0.1.45
Requires-Dist: fastapi>=0.68.0
Requires-Dist: uvicorn>=0.15.0
Requires-Dist: click>=8.0.0
Requires-Dist: rich-click>=1.7.0
Requires-Dist: httpx>=0.24.0
Requires-Dist: PyYAML>=6.0
Requires-Dist: langchain>=0.1.12
Requires-Dist: langchain_community>=0.3.20
Requires-Dist: playwright>=1.41.0
Requires-Dist: langchain-core==0.3.49
Requires-Dist: langchain-openai==0.3.11
Requires-Dist: langchain-anthropic==0.3.3
Requires-Dist: langchain-ollama==0.3.0
Requires-Dist: langchain-google-genai==2.1.2
Requires-Dist: langchain-google-vertexai>=0.1.0
Requires-Dist: langchain-deepseek>=0.1.3
Requires-Dist: python-dotenv>=1.0.0
Provides-Extra: web
Provides-Extra: dev
Requires-Dist: faker>=20.0.0; extra == "dev"
Requires-Dist: matplotlib>=3.8.0; extra == "dev"
Requires-Dist: tabulate>=0.9.0; extra == "dev"
Dynamic: license-file
